data_explorer/__init__.py
data_explorer/getter.py
senegal_economic_data_explorer-0.1.0.dist-info/licenses/AUTHORS.md
senegal_economic_data_explorer-0.1.0.dist-info/licenses/LICENSE
senegal_economic_data_explorer-0.1.0.dist-info/METADATA
senegal_economic_data_explorer-0.1.0.dist-info/WHEEL
senegal_economic_data_explorer-0.1.0.dist-info/top_level.txt
senegal_economic_data_explorer-0.1.0.dist-info/RECORD
