Metadata-Version: 2.4
Name: senegal-economic-data-explorer
Version: 0.1.0
Summary: Un package Python pour analyser les données économiques du Sénégal via l'API World Bank
Author-email: Maramata DIOP <maramatad@gmail.com>
Maintainer-email: Maramata DIOP <maramatad@gmail.com>
License: MIT
Project-URL: Homepage, https://github.com/MARAMATA/senegal-economic-data-explorer
Project-URL: Bug Tracker, https://github.com/MARAMATA/senegal-economic-data-explorer/issues
Project-URL: Documentation, https://github.com/MARAMATA/senegal-economic-data-explorer#readme
Project-URL: Source Code, https://github.com/MARAMATA/senegal-economic-data-explorer
Keywords: senegal,world bank,economic data,api,pandas,data analysis
Classifier: Development Status :: 3 - Alpha
Classifier: Intended Audience :: Developers
Classifier: Intended Audience :: Science/Research
Classifier: License :: OSI Approved :: MIT License
Classifier: Programming Language :: Python :: 3
Classifier: Programming Language :: Python :: 3.7
Classifier: Programming Language :: Python :: 3.8
Classifier: Programming Language :: Python :: 3.9
Classifier: Programming Language :: Python :: 3.10
Classifier: Programming Language :: Python :: 3.11
Classifier: Topic :: Scientific/Engineering :: Information Analysis
Classifier: Topic :: Software Development :: Libraries :: Python Modules
Requires-Python: >=3.7
License-File: LICENSE
License-File: AUTHORS.md
Requires-Dist: pandas>=1.3.0
Requires-Dist: requests>=2.26.0
Provides-Extra: dev
Requires-Dist: pytest>=7.0.0; extra == "dev"
Requires-Dist: pytest-cov>=3.0.0; extra == "dev"
Requires-Dist: black>=22.0.0; extra == "dev"
Requires-Dist: flake8>=4.0.0; extra == "dev"
Requires-Dist: mypy>=0.950; extra == "dev"
Requires-Dist: twine>=4.0.0; extra == "dev"
Requires-Dist: build>=0.8.0; extra == "dev"
Dynamic: license-file
